dsv2pulseq/__init__.py
dsv2pulseq/dsv_to_pulseq.py
dsv2pulseq/helper.py
dsv2pulseq/insert_twix_data.py
dsv2pulseq/read_dsv.py
dsv2pulseq/read_dsv_inf.py
dsv2pulseq/read_dsv_samples.py
dsv2pulseq/sequence.py
dsv2pulseq-0.1.3.dist-info/licenses/LICENSE
dsv2pulseq-0.1.3.dist-info/METADATA
dsv2pulseq-0.1.3.dist-info/WHEEL
dsv2pulseq-0.1.3.dist-info/entry_points.txt
dsv2pulseq-0.1.3.dist-info/top_level.txt
dsv2pulseq-0.1.3.dist-info/RECORD
