Metadata-Version: 2.4
Name: dsv2pulseq
Version: 0.1.3
Summary: Create Pulseq sequences from dsv.
Author-email: Marten Veldmann <marten.veldmann@dzne.de>
License: MIT License
Project-URL: Homepage, https://github.com/mavel101/dsv2pulseq
Keywords: pulseq,dsv,siemens,mri
Requires-Python: >=3.10
License-File: LICENSE
Requires-Dist: numpy
Requires-Dist: scipy
Requires-Dist: matplotlib
Requires-Dist: pypulseq>=1.4.2.post1
Requires-Dist: ismrmrd>=1.14.1
Requires-Dist: twixtools>=0.23
Dynamic: license-file
